simpleprompts/__init__.py
simpleprompts-0.1.3a1.dist-info/METADATA
simpleprompts-0.1.3a1.dist-info/WHEEL
simpleprompts-0.1.3a1.dist-info/top_level.txt
simpleprompts-0.1.3a1.dist-info/RECORD
