Metadata-Version: 2.4
Name: simpleprompts
Version: 0.1.3a1
Summary: A simple library for constructing LLM prompts
Author-email: Yasser Ahmed <yasserfawzi1029@outlook.com>
License-Expression: MIT
Project-URL: repository, https://github.com/Infrared1029/simpleprompts
Requires-Python: >=3.12
